AVMSpeechMath/__init__.py
AVMSpeechMath-0.0.5.dist-info/LICENSE
AVMSpeechMath-0.0.5.dist-info/METADATA
AVMSpeechMath-0.0.5.dist-info/WHEEL
AVMSpeechMath-0.0.5.dist-info/top_level.txt
AVMSpeechMath-0.0.5.dist-info/RECORD
