Metadata-Version: 2.1
Name: AVMSpeechMath
Version: 0.0.5
Summary: Perform voice operations in Spanish with Python.
Home-page: https://github.com/avmmodules/AVMSpeechMath
Author: AlejandroV
Author-email: avmmodules@gmail.com
License: UNKNOWN
Project-URL: Bug Tracker, https://github.com/avmmodules/AVMSpeechMath/issues
Platform: UNKNOWN
Classifier: Programming Language :: Python :: 3
Classifier: License :: OSI Approved :: MIT License
Classifier: Operating System :: OS Independent
Requires-Python: >=3.6
